pydhara/__init__.py
pydhara/py.typed
pydhara/catalog/__init__.py
pydhara/catalog/operators/__init__.py
pydhara/catalog/operators/basic.py
pydhara/catalog/operators/benchmark.py
pydhara/core/__init__.py
pydhara/core/common.py
pydhara/core/loader.py
pydhara/core/message_stream.py
pydhara/core/operator.py
pydhara/core/pipeline.py
pydhara/core/serializer.py
pydhara/zmq/__init__.py
pydhara/zmq/message_stream.py
pydhara/zmq/operator.py
pydhara/zmq/pipeline.py
pydhara-0.1.0.dist-info/METADATA
pydhara-0.1.0.dist-info/WHEEL
pydhara-0.1.0.dist-info/entry_points.txt
pydhara-0.1.0.dist-info/RECORD
