Metadata-Version: 2.4
Name: pydhara
Version: 0.1.0
Summary: Add your description here
Author-email: Mayank Thakur <mackv210w@gmail.com>
Requires-Python: >=3.12
Requires-Dist: loguru>=0.7.3
Requires-Dist: msgspec>=0.19.0
Requires-Dist: pyzmq>=26.4.0
